swift_code_metrics/__init__.py
swift_code_metrics/__main__.py
swift_code_metrics/_analyzer.py
swift_code_metrics/_graph_helpers.py
swift_code_metrics/_graphs_presenter.py
swift_code_metrics/_graphs_renderer.py
swift_code_metrics/_helpers.py
swift_code_metrics/_metrics.py
swift_code_metrics/_parser.py
swift_code_metrics/_report.py
swift_code_metrics/scm.py
swift_code_metrics/version.py
swift_code_metrics/tests/__init__.py
swift_code_metrics/tests/test_helper.py
swift_code_metrics/tests/test_integration.py
swift_code_metrics/tests/test_metrics.py
swift_code_metrics/tests/test_parser.py
swift_code_metrics-1.5.4.dist-info/LICENSE
swift_code_metrics-1.5.4.dist-info/METADATA
swift_code_metrics-1.5.4.dist-info/WHEEL
swift_code_metrics-1.5.4.dist-info/entry_points.txt
swift_code_metrics-1.5.4.dist-info/top_level.txt
swift_code_metrics-1.5.4.dist-info/RECORD
