Metadata-Version: 2.1
Name: swift-code-metrics
Version: 1.5.4
Summary: Code metrics analyzer for Swift projects.
Home-page: https://github.com/matsoftware/swift-code-metrics
Author: Mattia Campolese
Author-email: matsoftware@gmail.com
Classifier: Intended Audience :: Developers
Classifier: Programming Language :: Python :: 3
Classifier: License :: OSI Approved :: MIT License
Classifier: Operating System :: OS Independent
License-File: LICENSE
Requires-Dist: matplotlib >2
Requires-Dist: adjustText
Requires-Dist: pygraphviz >1.5
Requires-Dist: pyfunctional >1.2
Requires-Dist: numpy >1.22.0
Requires-Dist: dataclasses
